pexpect_serial/__init__.py
pexpect_serial/serial_spawn.py
pexpect_serial-0.1.0.dist-info/LICENSE
pexpect_serial-0.1.0.dist-info/METADATA
pexpect_serial-0.1.0.dist-info/WHEEL
pexpect_serial-0.1.0.dist-info/top_level.txt
pexpect_serial-0.1.0.dist-info/RECORD
