Metadata-Version: 2.1
Name: pexpect-serial
Version: 0.1.0
Summary: pexpect with pyserial
Home-page: https://github.com/highwall/pexpect-serial
Author: High Wall
Author-email: hiwall@126.com
License: UNKNOWN
Platform: UNKNOWN
Classifier: Programming Language :: Python :: 3
Classifier: License :: OSI Approved :: MIT License
Classifier: Operating System :: OS Independent
Requires-Dist: pexpect
Requires-Dist: pyserial
